nimbusinator/__init__.py
nimbusinator/colour_table.py
nimbusinator/command.py
nimbusinator/nimbus.py
nimbusinator/readme-logo.py
nimbusinator/supported_control_keys.py
nimbusinator/tools.py
nimbusinator/videostream.py
nimbusinator/welcome.py
nimbusinator/data/floppy-dash1.wav
nimbusinator/data/floppy-dash2.wav
nimbusinator/data/floppy-dash3.wav
nimbusinator/data/floppy-dash4.wav
nimbusinator/data/floppy-dot1.wav
nimbusinator/data/floppy-dot2.wav
nimbusinator/data/floppy-dot3.wav
nimbusinator/data/floppy-dot4.wav
nimbusinator/data/font0-alpha.png
nimbusinator/data/font0.png
nimbusinator/data/font1-alpha.png
nimbusinator/data/font1.png
nimbusinator/data/rm-nimbus-logo.bmp
nimbusinator/data/rm-nimbus-logo.png
nimbusinator-0.2.2.dist-info/METADATA
nimbusinator-0.2.2.dist-info/WHEEL
nimbusinator-0.2.2.dist-info/top_level.txt
nimbusinator-0.2.2.dist-info/RECORD
