Metadata-Version: 2.1
Name: nimbusinator
Version: 0.2.2
Summary: RM Nimbus GUI for Python
Home-page: https://github.com/adamstimb/nimbusinator
Author: Tim Adams
Author-email: adamstimb@gmail.com
License: UNKNOWN
Platform: UNKNOWN
Classifier: Programming Language :: Python :: 3
Classifier: License :: OSI Approved :: MIT License
Classifier: Operating System :: OS Independent
Requires-Python: >=3.6
Requires-Dist: PySDL2
Requires-Dist: Pillow
Requires-Dist: numpy
Requires-Dist: simpleaudio
Requires-Dist: pynput (==1.4.5)
Requires-Dist: psutil
Requires-Dist: pygame (<2.0,>=1.9.3) ; python_version != "3.3"
